[
{ "key": "ctrl+right",             "command": "cursorWordEndRight",
                                     "when": "editorTextFocus" },
{ "key": "shift+ctrl+right",       "command": "cursorWordEndRightSelect",
                                     "when": "editorTextFocus" },
{ "key": "ctrl+left",              "command": "cursorWordStartLeft",
                                     "when": "editorTextFocus" },
{ "key": "shift+ctrl+left",        "command": "cursorWordStartLeftSelect",
                                     "when": "editorTextFocus" },
{ "key": "ctrl+f",                 "command": "actions.find" },
{ "key": "shift+cmd+o",            "command": "workbench.action.quickOpen" },
{ "key": "shift+ctrl+down",              "command": "editor.action.moveLinesDownAction",
                                     "when": "editorTextFocus && !editorReadonly" },
{ "key": "shift+ctrl+up",                "command": "editor.action.moveLinesUpAction",
                                     "when": "editorTextFocus && !editorReadonly" }

]